Car_Parking-Exercises/Car_Parking_System_VHDL.vhd
library ieee;
use ieee.std_logic_1164.all;
use ieee.numeric_std.all;

entity Car_Parking_System_VHDL is
port 
(
    clk, reset_n                 : in std_logic;
    front_sensor, back_sensor   : in std_logic;
    password_1, password_2      : in std_logic_vector(1 downto 0);
    pswd_in                     : in std_logic;  -- Nuovo input per rilevare attivazione tastiera
    GREEN_LED, RED_LED           : out std_logic;
    HEX_1, HEX_2                : out std_logic_vector(6 downto 0);
    car_count                   : out std_logic_vector(7 downto 0)  -- Contatore auto (0-255)
);
end Car_Parking_System_VHDL;

architecture Behavioral of Car_Parking_System_VHDL is 
    type state_types is (IDLE, WAIT_PASSWORD, WRONG_PASS, 
                        RIGHT_PASS, STOP, TIMEOUT);  -- Aggiunto stato TIMEOUT
    signal current_state, next_state: state_types;
    signal counter_wait: unsigned(3 downto 0) := (others => '0');
    signal counter_wrong: unsigned(1 downto 0) := (others => '0');
    signal red_tmp, green_tmp: std_logic;
    signal blink_counter: unsigned(1 downto 0) := (others => '0');
    
    -- Nuovi segnali aggiunti
    signal password_accepted: std_logic := '0';
    signal password_checked: std_logic := '0';
    signal timeout_counter: unsigned(3 downto 0) := (others => '0');
    signal internal_car_count: unsigned(7 downto 0) := (others => '0');
    signal pswd_activity: std_logic := '0';

begin
    -- State register
    process(clk, reset_n)
    begin
        if(reset_n='0') then
            current_state <= IDLE;
            password_accepted <= '0';
            password_checked <= '0';
            pswd_activity <= '0';
        elsif(rising_edge(clk)) then
            current_state <= next_state;
            
            -- Reset password_accepted quando si torna in IDLE o WAIT_PASSWORD
            if current_state = IDLE then
                password_accepted <= '0';
                password_checked <= '0';
                pswd_activity <= '0';
            elsif current_state = WAIT_PASSWORD then
                password_checked <= '0';
                -- Rileva attività sulla tastiera
                if pswd_in = '1' then
                    pswd_activity <= '1';
                end if;
            end if;
        end if; 
    end process;

    -- Transition process
    process(current_state, front_sensor, back_sensor, counter_wait, counter_wrong, 
            password_1, password_2, password_accepted, password_checked, timeout_counter, pswd_activity)
    begin
        case current_state is
            when IDLE =>  
                if front_sensor = '1' then
                    next_state <= WAIT_PASSWORD;
                else
                    next_state <= IDLE;
                end if;
                
            when WAIT_PASSWORD =>
                if timeout_counter >= 10 and pswd_activity = '0' then
                    next_state <= TIMEOUT;  -- Timeout se nessuna attività dopo 10 cicli
                elsif counter_wait < 9 then
                    next_state <= WAIT_PASSWORD;
                else
                    if (password_1 = "01" and password_2 = "10") then
                        next_state <= RIGHT_PASS;
                        password_accepted <= '1';
                        password_checked <= '1';
                        --reset password!!!!!!!!!!!
                        
                    else
                        next_state <= WRONG_PASS;
                        password_checked <= '1';
                    end if;
                end if;
                
            when WRONG_PASS => 
                if counter_wrong >= 2 then
                    next_state <= WAIT_PASSWORD;
                else
                    next_state <= WRONG_PASS;
                end if;
                
            when RIGHT_PASS =>
                if front_sensor = '1' and password_checked = '1' then
                    next_state <= STOP;
                elsif back_sensor = '1' then
                    next_state <= IDLE;
                else
                    next_state <= RIGHT_PASS;
                end if;
                
            when STOP => 
                if back_sensor = '1' then
                    next_state <= WAIT_PASSWORD;
                else
                    next_state <= STOP;
                end if;
                
            when TIMEOUT =>
                -- Ritorna a IDLE quando la macchina si allontana
                if front_sensor = '0' then
                    next_state <= IDLE;
                else
                    next_state <= TIMEOUT;
                end if;
                
        end case; 
    end process;

    -- Counter Process for WAIT_PASSWORD
    process(clk, reset_n)
    begin
        if reset_n = '0' then
            counter_wait <= (others => '0');
        elsif rising_edge(clk) then
            if current_state = WAIT_PASSWORD then
                if counter_wait < 9 then
                    counter_wait <= counter_wait + 1;
                end if;
            else
                counter_wait <= (others => '0');
            end if;
        end if;
    end process;

    -- Counter Process for WRONG_PASS
    process(clk, reset_n)
    begin
        if reset_n = '0' then
            counter_wrong <= (others => '0');
        elsif rising_edge(clk) then
            if current_state = WRONG_PASS then
                if counter_wrong < 3 then
                    counter_wrong <= counter_wrong + 1;
                else
                    counter_wrong <= (others => '0');
                end if;
            else
                counter_wrong <= (others => '0');
            end if;
        end if;
    end process;

    -- Timeout counter
    process(clk, reset_n)
    begin
        if reset_n = '0' then
            timeout_counter <= (others => '0');
        elsif rising_edge(clk) then
            if current_state = WAIT_PASSWORD then
                if timeout_counter < 15 then  -- Contatore timeout più lungo
                    timeout_counter <= timeout_counter + 1;
                end if;
            else
                timeout_counter <= (others => '0');
            end if;
        end if;
    end process;

    -- Car counter - incrementa quando una macchina entra correttamente
    process(clk, reset_n)
    begin
        if reset_n = '0' then
            internal_car_count <= (others => '0');
        elsif rising_edge(clk) then
            -- Incrementa il contatore quando si passa da RIGHT_PASS a IDLE (macchina entrata)
            if current_state = RIGHT_PASS and next_state = IDLE then
                internal_car_count <= internal_car_count + 1;
            end if;
        end if;
    end process;

    car_count <= std_logic_vector(internal_car_count);

    -- Blink counter
    process(clk, reset_n)
    begin
        if reset_n = '0' then
            blink_counter <= (others => '0');
        elsif rising_edge(clk) then
            blink_counter <= blink_counter + 1;
        end if;
    end process;

    -- Output process
    process(clk)
        variable blink_fast : std_logic;
    begin
        blink_fast := blink_counter(0);
        
        if rising_edge(clk) then
            case current_state is
                when IDLE => 
                    green_tmp <= '0';
                    red_tmp   <= '0';
                    HEX_1     <= "1111111"; -- off
                    HEX_2     <= "1111111"; -- off
                    
                when WAIT_PASSWORD =>
                    green_tmp <= '0';
                    red_tmp   <= '1';
                    HEX_1     <= "0000110"; -- E
                    HEX_2     <= "0101011"; -- n
                    
                when WRONG_PASS =>
                    green_tmp <= '0';
                    red_tmp   <= blink_fast;
                    HEX_1     <= "0000110"; -- E
                    HEX_2     <= "0000110"; -- E
                    
                when RIGHT_PASS =>
                    green_tmp <= blink_fast;
                    red_tmp   <= '0';
                    HEX_1     <= "0000010"; -- G
                    HEX_2     <= "1000000"; -- O
                    
                when STOP => 
                    green_tmp <= '0';
                    red_tmp   <= blink_fast;
                    HEX_1     <= "0100100"; -- S
                    HEX_2     <= "0001100"; -- P
                    
                when TIMEOUT =>
                    green_tmp <= '0';
                    red_tmp   <= blink_fast;
                    HEX_1     <= "0000111"; -- T (nuovo carattere)
                    HEX_2     <= "1000000"; -- O
                    
            end case;
        end if;
    end process;
    
    GREEN_LED <= green_tmp;
    RED_LED   <= red_tmp;

end architecture;

Car_Parking-Exercises/test.vhd
library ieee;
use ieee.std_logic_1164.all;
use ieee.numeric_std.all;

entity test is
end test;

architecture testbench of test is
    component Car_Parking_System_VHDL is
    port 
    (
        clk, reset_n                 : in std_logic;
        front_sensor, back_sensor   : in std_logic;
        password_1, password_2      : in std_logic_vector(1 downto 0);
        pswd_in                     : in std_logic;
        GREEN_LED, RED_LED           : out std_logic;
        HEX_1, HEX_2                : out std_logic_vector(6 downto 0);
        car_count                   : out std_logic_vector(7 downto 0)
    );
    end component;

    -- Test signals
    signal clk_tb : std_logic := '0';
    signal reset_n_tb : std_logic := '0';
    signal front_sensor_tb, back_sensor_tb : std_logic := '0';
    signal password_1_tb, password_2_tb : std_logic_vector(1 downto 0) := "00";
    signal pswd_in_tb : std_logic := '0';
    signal GREEN_LED_tb, RED_LED_tb : std_logic;
    signal HEX_1_tb, HEX_2_tb : std_logic_vector(6 downto 0);
    signal car_count_tb : std_logic_vector(7 downto 0);

    -- Clock period
    constant clk_period : time := 20 ns;

begin
    -- Clock generation
    clk_tb <= not clk_tb after clk_period/2;

    -- DUT instantiation
    DUT: Car_Parking_System_VHDL
        port map (
            clk => clk_tb,
            reset_n => reset_n_tb,
            front_sensor => front_sensor_tb,
            back_sensor => back_sensor_tb,
            password_1 => password_1_tb,
            password_2 => password_2_tb,
            pswd_in => pswd_in_tb,
            GREEN_LED => GREEN_LED_tb,
            RED_LED => RED_LED_tb,
            HEX_1 => HEX_1_tb,
            HEX_2 => HEX_2_tb,
            car_count => car_count_tb
        );

    -- Stimulus process
    stimulus: process
    begin
        -- Inizializzazione
        reset_n_tb <= '0';
        front_sensor_tb <= '0';
        back_sensor_tb <= '0';
        password_1_tb <= "00";
        password_2_tb <= "00";
        pswd_in_tb <= '0';
        wait for 100 ns;
        
        -- Deassert reset
        reset_n_tb <= '1';
        wait for 100 ns;
        
        -- Scenario 1: Normal Entry
        report "=== Scenario 1: Normal Entry ===";
        front_sensor_tb <= '1';
        wait for 200 ns;
        
        -- Simula attività tastiera dopo qualche ciclo
        wait for 60 ns;
        pswd_in_tb <= '1';
        wait for clk_period;
        pswd_in_tb <= '0';
        
        -- Inserimento password corretta
        password_1_tb <= "01";
        password_2_tb <= "10";
        wait for 200 ns;
        
        -- Macchina passa
        back_sensor_tb <= '1';
        wait for 100 ns;
        back_sensor_tb <= '0';
        front_sensor_tb <= '0';
        wait for 100 ns;
        
        -- Scenario 2: Wrong Password
        report "=== Scenario 2: Wrong Password ===";
        front_sensor_tb <= '1';
        wait for 200 ns;
        
        pswd_in_tb <= '1';
        wait for clk_period;
        pswd_in_tb <= '0';
        
        -- Password errata
        password_1_tb <= "00";
        password_2_tb <= "00";
        wait for 200 ns;
        
        -- Password corretta
        password_1_tb <= "01";
        password_2_tb <= "10";
        wait for 200 ns;
        
        back_sensor_tb <= '1';
        wait for 100 ns;
        back_sensor_tb <= '0';
        front_sensor_tb <= '0';
        wait for 100 ns;
        
        -- Scenario 3: Multiple Cars
        report "=== Scenario 3: Multiple Cars ===";
        front_sensor_tb <= '1';
        wait for 200 ns;
        
        pswd_in_tb <= '1';
        wait for clk_period;
        pswd_in_tb <= '0';
        
        password_1_tb <= "01";
        password_2_tb <= "10";
        wait for 100 ns;
        
        -- Seconda macchina arriva prima che la prima passi
        front_sensor_tb <= '1'; -- Rimane alto per seconda macchina
        wait for 100 ns;
        
        back_sensor_tb <= '1'; -- Prima macchina passa
        wait for 100 ns;
        back_sensor_tb <= '0';
        
        -- Password per seconda macchina
        pswd_in_tb <= '1';
        wait for clk_period;
        pswd_in_tb <= '0';
        
        password_1_tb <= "01";
        password_2_tb <= "10";
        wait for 200 ns;
        
        back_sensor_tb <= '1';
        wait for 100 ns;
        back_sensor_tb <= '0';
        front_sensor_tb <= '0';
        wait for 100 ns;
        
        -- Scenario 4: Timeout
        report "=== Scenario 4: Timeout ===";
        front_sensor_tb <= '1';
        wait for 400 ns; -- Aspetta senza inserire password
        
        -- Macchina si allontana
        front_sensor_tb <= '0';
        wait for 100 ns;
        
        -- Scenario 5: Reset
        report "=== Scenario 5: Reset ===";
        front_sensor_tb <= '1';
        wait for 100 ns;
        
        pswd_in_tb <= '1';
        wait for clk_period;
        pswd_in_tb <= '0';
        
        password_1_tb <= "01";
        password_2_tb <= "10";
        wait for 100 ns;
        
        -- Reset durante RIGHT_PASS
        reset_n_tb <= '0';
        wait for 100 ns;
        reset_n_tb <= '1';
        
        wait for 200 ns;
        
        report "=== Tutti gli scenari completati ===";
        wait;
    end process;

end testbench;

Car_Parking-Exercises/sim.vcd
$date
  Tue Nov 18 23:31:33 2025
$end
$version
  GHDL v0
$end
$timescale
  1 fs
$end
$scope module standard $end
$upscope $end
$scope module std_logic_1164 $end
$upscope $end
$scope module numeric_std $end
$upscope $end
$scope module test $end
$var reg 1 ! clk_tb $end
$var reg 1 " reset_n_tb $end
$var reg 1 # front_sensor_tb $end
$var reg 1 $ back_sensor_tb $end
$var reg 2 % password_1_tb[1:0] $end
$var reg 2 & password_2_tb[1:0] $end
$var reg 1 ' pswd_in_tb $end
$var reg 1 ( green_led_tb $end
$var reg 1 ) red_led_tb $end
$var reg 7 * hex_1_tb[6:0] $end
$var reg 7 + hex_2_tb[6:0] $end
$var reg 8 , car_count_tb[7:0] $end
$scope module dut $end
$var reg 1 - clk $end
$var reg 1 . reset_n $end
$var reg 1 / front_sensor $end
$var reg 1 0 back_sensor $end
$var reg 2 1 password_1[1:0] $end
$var reg 2 2 password_2[1:0] $end
$var reg 1 3 pswd_in $end
$var reg 1 4 green_led $end
$var reg 1 5 red_led $end
$var reg 7 6 hex_1[6:0] $end
$var reg 7 7 hex_2[6:0] $end
$var reg 8 8 car_count[7:0] $end
$comment current_state is not handled $end
$comment next_state is not handled $end
$var reg 4 9 counter_wait[3:0] $end
$var reg 2 : counter_wrong[1:0] $end
$var reg 1 ; red_tmp $end
$var reg 1 < green_tmp $end
$var reg 2 = blink_counter[1:0] $end
$var reg 1 > password_accepted $end
$var reg 1 ? password_checked $end
$var reg 4 @ timeout_counter[3:0] $end
$var reg 8 A internal_car_count[7:0] $end
$var reg 1 B pswd_activity $end
$upscope $end
$upscope $end
$enddefinitions $end
#0
0!
0"
0#
0$
b00 %
b00 &
0'
U(
U)
bUUUUUUU *
bUUUUUUU +
b00000000 ,
0-
0.
0/
00
b00 1
b00 2
03
U4
U5
bUUUUUUU 6
bUUUUUUU 7
b00000000 8
b0000 9
b00 :
U;
U<
b00 =
0>
0?
b0000 @
b00000000 A
0B
#10000000
1!
0(
0)
b1111111 *
b1111111 +
1-
04
05
b1111111 6
b1111111 7
0;
0<
#20000000
0!
0-
#30000000
1!
1-
#40000000
0!
0-
#50000000
1!
1-
#60000000
0!
0-
#70000000
1!
1-
#80000000
0!
0-
#90000000
1!
1-
#100000000
0!
1"
0-
1.
#110000000
1!
1-
b01 =
#120000000
0!
0-
#130000000
1!
1-
b10 =
#140000000
0!
0-
#150000000
1!
1-
b11 =
#160000000
0!
0-
#170000000
1!
1-
b00 =
#180000000
0!
0-
#190000000
1!
1-
b01 =
#200000000
0!
1#
0-
1/
#210000000
1!
1-
b10 =
#220000000
0!
0-
#230000000
1!
1)
b0000110 *
b0101011 +
1-
15
b0000110 6
b0101011 7
b0001 9
1;
b11 =
b0001 @
#240000000
0!
0-
#250000000
1!
1-
b0010 9
b00 =
b0010 @
#260000000
0!
0-
#270000000
1!
1-
b0011 9
b01 =
b0011 @
#280000000
0!
0-
#290000000
1!
1-
b0100 9
b10 =
b0100 @
#300000000
0!
0-
#310000000
1!
1-
b0101 9
b11 =
b0101 @
#320000000
0!
0-
#330000000
1!
1-
b0110 9
b00 =
b0110 @
#340000000
0!
0-
#350000000
1!
1-
b0111 9
b01 =
b0111 @
#360000000
0!
0-
#370000000
1!
1-
b1000 9
b10 =
b1000 @
#380000000
0!
0-
#390000000
1!
1-
b1001 9
b11 =
X?
b1001 @
#400000000
0!
0-
#410000000
1!
1-
b00 =
b1010 @
#420000000
0!
0-
#430000000
1!
0)
b0000110 +
1-
05
b0000110 7
b0000 9
b01 :
0;
b01 =
b0000 @
#440000000
0!
0-
#450000000
1!
1)
1-
15
b10 :
1;
b10 =
#460000000
0!
1'
0-
13
#470000000
1!
0)
1-
05
b11 :
0;
b11 =
#480000000
0!
b01 %
b10 &
0'
0-
b01 1
b10 2
03
#490000000
1!
1)
b0101011 +
1-
15
b0101011 7
b0001 9
b00 :
1;
b00 =
b0001 @
#500000000
0!
0-
#510000000
1!
1-
b0010 9
b01 =
b0010 @
#520000000
0!
0-
#530000000
1!
1-
b0011 9
b10 =
b0011 @
#540000000
0!
0-
#550000000
1!
1-
b0100 9
b11 =
b0100 @
#560000000
0!
0-
#570000000
1!
1-
b0101 9
b00 =
b0101 @
#580000000
0!
0-
#590000000
1!
1-
b0110 9
b01 =
b0110 @
#600000000
0!
0-
#610000000
1!
1-
b0111 9
b10 =
b0111 @
#620000000
0!
0-
#630000000
1!
1-
b1000 9
b11 =
b1000 @
#640000000
0!
0-
#650000000
1!
1-
b1001 9
b00 =
X>
b1001 @
#660000000
0!
0-
#670000000
1!
1-
b01 =
b1010 @
#680000000
0!
1$
0-
10
#690000000
1!
1(
0)
b0000010 *
b1000000 +
b00000001 ,
1-
14
05
b0000010 6
b1000000 7
b00000001 8
b0000 9
0;
1<
b10 =
b0000 @
b00000001 A
#700000000
0!
0-
#710000000
1!
0(
b1111111 *
b1111111 +
1-
04
b1111111 6
b1111111 7
0<
b11 =
#720000000
0!
0-
#730000000
1!
1)
b0000110 *
b0101011 +
1-
15
b0000110 6
b0101011 7
b0001 9
1;
b00 =
b0001 @
#740000000
0!
0-
#750000000
1!
1-
b0010 9
b01 =
b0010 @
#760000000
0!
0-
#770000000
1!
1-
b0011 9
b10 =
b0011 @
#780000000
0!
0#
0$
0-
0/
00
#790000000
1!
1-
b0100 9
b11 =
b0100 @
#800000000
0!
0-
#810000000
1!
1-
b0101 9
b00 =
b0101 @
#820000000
0!
0-
#830000000
1!
1-
b0110 9
b01 =
b0110 @
#840000000
0!
0-
#850000000
1!
1-
b0111 9
b10 =
b0111 @
#860000000
0!
0-
#870000000
1!
1-
b1000 9
b11 =
b1000 @
#880000000
0!
1#
0-
1/
#890000000
1!
1-
b1001 9
b00 =
b1001 @
#900000000
0!
0-
#910000000
1!
1-
b01 =
b1010 @
#920000000
0!
0-
#930000000
1!
1(
0)
b0000010 *
b1000000 +
1-
14
05
b0000010 6
b1000000 7
b0000 9
0;
1<
b10 =
b0000 @
#940000000
0!
0-
#950000000
1!
0(
1-
04
0<
b11 =
#960000000
0!
0-
#970000000
1!
1(
1-
14
1<
b00 =
#980000000
0!
0-
#990000000
1!
0(
1-
04
0<
b01 =
#1000000000
0!
0-
#1010000000
1!
1(
1-
14
1<
b10 =
#1020000000
0!
0-
#1030000000
1!
0(
1-
04
0<
b11 =
#1040000000
0!
0-
#1050000000
1!
1(
1-
14
1<
b00 =
#1060000000
0!
0-
#1070000000
1!
0(
1-
04
0<
b01 =
#1080000000
0!
1'
0-
13
#1090000000
1!
1(
1-
14
1<
b10 =
#1100000000
0!
b00 %
b00 &
0'
0-
b00 1
b00 2
03
#1110000000
1!
0(
1-
04
0<
b11 =
#1120000000
0!
0-
#1130000000
1!
1(
1-
14
1<
b00 =
#1140000000
0!
0-
#1150000000
1!
0(
1-
04
0<
b01 =
#1160000000
0!
0-
#1170000000
1!
1(
1-
14
1<
b10 =
#1180000000
0!
0-
#1190000000
1!
0(
1-
04
0<
b11 =
#1200000000
0!
0-
#1210000000
1!
1(
1-
14
1<
b00 =
#1220000000
0!
0-
#1230000000
1!
0(
1-
04
0<
b01 =
#1240000000
0!
0-
#1250000000
1!
1(
1-
14
1<
b10 =
#1260000000
0!
0-
#1270000000
1!
0(
1-
04
0<
b11 =
#1280000000
0!
0-
#1290000000
1!
1(
1-
14
1<
b00 =
#1300000000
0!
b01 %
b10 &
0-
b01 1
b10 2
#1310000000
1!
0(
1-
04
0<
b01 =
#1320000000
0!
0-
#1330000000
1!
1(
1-
14
1<
b10 =
#1340000000
0!
0-
#1350000000
1!
0(
1-
04
0<
b11 =
#1360000000
0!
0-
#1370000000
1!
1(
1-
14
1<
b00 =
#1380000000
0!
0-
#1390000000
1!
0(
1-
04
0<
b01 =
#1400000000
0!
0-
#1410000000
1!
1(
1-
14
1<
b10 =
#1420000000
0!
0-
#1430000000
1!
0(
1-
04
0<
b11 =
#1440000000
0!
0-
#1450000000
1!
1(
1-
14
1<
b00 =
#1460000000
0!
0-
#1470000000
1!
0(
1-
04
0<
b01 =
#1480000000
0!
0-
#1490000000
1!
1(
1-
14
1<
b10 =
#1500000000
0!
1$
0-
10
#1510000000
1!
0(
b00000010 ,
1-
04
b00000010 8
0<
b11 =
b00000010 A
#1520000000
0!
0-
#1530000000
1!
b1111111 *
b1111111 +
1-
b1111111 6
b1111111 7
b00 =
#1540000000
0!
0-
#1550000000
1!
1)
b0000110 *
b0101011 +
1-
15
b0000110 6
b0101011 7
b0001 9
1;
b01 =
b0001 @
#1560000000
0!
0-
#1570000000
1!
1-
b0010 9
b10 =
b0010 @
#1580000000
0!
0-
#1590000000
1!
1-
b0011 9
b11 =
b0011 @
#1600000000
0!
0#
0$
0-
0/
00
#1610000000
1!
1-
b0100 9
b00 =
b0100 @
#1620000000
0!
0-
#1630000000
1!
1-
b0101 9
b01 =
b0101 @
#1640000000
0!
0-
#1650000000
1!
1-
b0110 9
b10 =
b0110 @
#1660000000
0!
0-
#1670000000
1!
1-
b0111 9
b11 =
b0111 @
#1680000000
0!
0-
#1690000000
1!
1-
b1000 9
b00 =
b1000 @
#1700000000
0!
1#
0-
1/
#1710000000
1!
1-
b1001 9
b01 =
b1001 @
#1720000000
0!
0-
#1730000000
1!
1-
b10 =
b1010 @
#1740000000
0!
0-
#1750000000
1!
0)
b0000010 *
b1000000 +
1-
05
b0000010 6
b1000000 7
b0000 9
0;
b11 =
b0000 @
#1760000000
0!
0-
#1770000000
1!
1(
1-
14
1<
b00 =
#1780000000
0!
0-
#1790000000
1!
0(
1-
04
0<
b01 =
#1800000000
0!
0-
#1810000000
1!
1(
1-
14
1<
b10 =
#1820000000
0!
0-
#1830000000
1!
0(
1-
04
0<
b11 =
#1840000000
0!
0-
#1850000000
1!
1(
1-
14
1<
b00 =
#1860000000
0!
0-
#1870000000
1!
0(
1-
04
0<
b01 =
#1880000000
0!
0-
#1890000000
1!
1(
1-
14
1<
b10 =
#1900000000
0!
1'
0-
13
#1910000000
1!
0(
1-
04
0<
b11 =
#1920000000
0!
0'
0-
03
#1930000000
1!
1(
1-
14
1<
b00 =
#1940000000
0!
0-
#1950000000
1!
0(
1-
04
0<
b01 =
#1960000000
0!
0-
#1970000000
1!
1(
1-
14
1<
b10 =
#1980000000
0!
0-
#1990000000
1!
0(
1-
04
0<
b11 =
#2000000000
0!
0-
#2010000000
1!
1(
1-
14
1<
b00 =
#2020000000
0!
0-
#2030000000
1!
0(
1-
04
0<
b01 =
#2040000000
0!
0-
#2050000000
1!
1(
1-
14
1<
b10 =
#2060000000
0!
0-
#2070000000
1!
0(
1-
04
0<
b11 =
#2080000000
0!
0-
#2090000000
1!
1(
1-
14
1<
b00 =
#2100000000
0!
0-
#2110000000
1!
0(
1-
04
0<
b01 =
#2120000000
0!
1$
0-
10
#2130000000
1!
1(
b00000011 ,
1-
14
b00000011 8
1<
b10 =
b00000011 A
#2140000000
0!
0-
#2150000000
1!
0(
b1111111 *
b1111111 +
1-
04
b1111111 6
b1111111 7
0<
b11 =
#2160000000
0!
0-
#2170000000
1!
1)
b0000110 *
b0101011 +
1-
15
b0000110 6
b0101011 7
b0001 9
1;
b00 =
b0001 @
#2180000000
0!
0-
#2190000000
1!
1-
b0010 9
b01 =
b0010 @
#2200000000
0!
0-
#2210000000
1!
1-
b0011 9
b10 =
b0011 @
#2220000000
0!
0$
1'
0-
00
13
#2230000000
1!
1-
b0100 9
b11 =
b0100 @
1B
#2240000000
0!
0'
0-
03
#2250000000
1!
1-
b0101 9
b00 =
b0101 @
#2260000000
0!
0-
#2270000000
1!
1-
b0110 9
b01 =
b0110 @
#2280000000
0!
0-
#2290000000
1!
1-
b0111 9
b10 =
b0111 @
#2300000000
0!
0-
#2310000000
1!
1-
b1000 9
b11 =
b1000 @
#2320000000
0!
0-
#2330000000
1!
1-
b1001 9
b00 =
b1001 @
#2340000000
0!
0-
#2350000000
1!
1-
b01 =
b1010 @
#2360000000
0!
0-
#2370000000
1!
1(
0)
b0000010 *
b1000000 +
1-
14
05
b0000010 6
b1000000 7
b0000 9
0;
1<
b10 =
b0000 @
#2380000000
0!
0-
#2390000000
1!
0(
1-
04
0<
b11 =
#2400000000
0!
0-
#2410000000
1!
1(
1-
14
1<
b00 =
#2420000000
0!
0-
#2430000000
1!
0(
1-
04
0<
b01 =
#2440000000
0!
1$
0-
10
#2450000000
1!
1(
b00000100 ,
1-
14
b00000100 8
1<
b10 =
b00000100 A
#2460000000
0!
0-
#2470000000
1!
0(
b1111111 *
b1111111 +
1-
04
b1111111 6
b1111111 7
0<
b11 =
0B
#2480000000
0!
0-
#2490000000
1!
1)
b0000110 *
b0101011 +
1-
15
b0000110 6
b0101011 7
b0001 9
1;
b00 =
b0001 @
#2500000000
0!
0-
#2510000000
1!
1-
b0010 9
b01 =
b0010 @
#2520000000
0!
0-
#2530000000
1!
1-
b0011 9
b10 =
b0011 @
#2540000000
0!
0#
0$
0-
0/
00
#2550000000
1!
1-
b0100 9
b11 =
b0100 @
#2560000000
0!
0-
#2570000000
1!
1-
b0101 9
b00 =
b0101 @
#2580000000
0!
0-
#2590000000
1!
1-
b0110 9
b01 =
b0110 @
#2600000000
0!
0-
#2610000000
1!
1-
b0111 9
b10 =
b0111 @
#2620000000
0!
0-
#2630000000
1!
1-
b1000 9
b11 =
b1000 @
#2640000000
0!
1#
0-
1/
#2650000000
1!
1-
b1001 9
b00 =
b1001 @
#2660000000
0!
0-
#2670000000
1!
1-
b01 =
b1010 @
#2680000000
0!
0-
#2690000000
1!
1(
0)
b0000010 *
b1000000 +
1-
14
05
b0000010 6
b1000000 7
b0000 9
0;
1<
b10 =
b0000 @
#2700000000
0!
0-
#2710000000
1!
0(
1-
04
0<
b11 =
#2720000000
0!
0-
#2730000000
1!
1(
1-
14
1<
b00 =
#2740000000
0!
0-
#2750000000
1!
0(
1-
04
0<
b01 =
#2760000000
0!
0-
#2770000000
1!
1(
1-
14
1<
b10 =
#2780000000
0!
0-
#2790000000
1!
0(
1-
04
0<
b11 =
#2800000000
0!
0-
#2810000000
1!
1(
1-
14
1<
b00 =
#2820000000
0!
0-
#2830000000
1!
0(
1-
04
0<
b01 =
#2840000000
0!
0-
#2850000000
1!
1(
1-
14
1<
b10 =
#2860000000
0!
0-
#2870000000
1!
0(
1-
04
0<
b11 =
#2880000000
0!
0-
#2890000000
1!
1(
1-
14
1<
b00 =
#2900000000
0!
0-
#2910000000
1!
0(
1-
04
0<
b01 =
#2920000000
0!
0-
#2930000000
1!
1(
1-
14
1<
b10 =
#2940000000
0!
0-
#2950000000
1!
0(
1-
04
0<
b11 =
#2960000000
0!
0-
#2970000000
1!
1(
1-
14
1<
b00 =
#2980000000
0!
0-
#2990000000
1!
0(
1-
04
0<
b01 =
