Car_Parking_System_VHDL.vhd
library ieee;
use ieee.std_logic_1164.all;
use ieee.numeric_std.all;

entity Car_Parking_System_VHDL is
port 
(
    clk, reset_n                 : in std_logic;
    front_sensor, back_sensor   : in std_logic;
    password_1, password_2      : in std_logic_vector(1 downto 0);
    GREEN_LED, RED_LED           : out std_logic;
    HEX_1, HEX_2                : out std_logic_vector(6 downto 0)
);
end Car_Parking_System_VHDL;

architecture Behavioral of Car_Parking_System_VHDL is 
    type state_types is (IDLE, WAIT_PASSWORD, WRONG_PASS, 
                        RIGHT_PASS, STOP);
    signal current_state, next_state: state_types;
    signal counter_wait: unsigned(3 downto 0) := (others => '0');
    signal counter_wrong: unsigned(1 downto 0) := (others => '0');
    signal red_tmp, green_tmp: std_logic;
    signal blink_counter: unsigned(1 downto 0) := (others => '0');

    signal password_accepted: std_logic := '0';
    signal password_checked: std_logic := '0';

begin
    -- State register
    process(clk, reset_n)
    begin
        if(reset_n='0') then
            current_state <= IDLE;
            password_accepted <= '0';
            password_checked <= '0';
        elsif(rising_edge(clk)) then
            current_state <= next_state;
            
            -- Reset password_accepted when returns to IDLE or WAIT_PASSWORD
            if current_state = IDLE then
                password_accepted <= '0';
                password_checked <= '0';
            elsif current_state = WAIT_PASSWORD then
                password_checked <= '0';
            end if;
        end if; 
    end process;

    -- Transition process
    process(current_state, front_sensor, back_sensor, counter_wait, counter_wrong, 
            password_1, password_2, password_accepted, password_checked)
    begin
        case current_state is
            when IDLE =>  
                if front_sensor = '1' then
                    next_state <= WAIT_PASSWORD;
                else
                    next_state <= IDLE;
                end if;
                
            when WAIT_PASSWORD =>
                if counter_wait < 9 then
                    next_state <= WAIT_PASSWORD;
                else
                    if (password_1 = "01" and password_2 = "10") then
                        next_state <= RIGHT_PASS;
                        password_accepted <= '1';
                        password_checked <= '1';
                    else
                        next_state <= WRONG_PASS;
                        password_checked <= '1';
                    end if;
                end if;
                
            when WRONG_PASS => 
                if counter_wrong >= 2 then
                    next_state <= WAIT_PASSWORD;
                else
                    next_state <= WRONG_PASS;
                end if;
                
            when RIGHT_PASS =>
                if front_sensor = '1' and password_checked = '1' then
                    next_state <= STOP;
                elsif back_sensor = '1' then
                    next_state <= IDLE;
                else
                    next_state <= RIGHT_PASS;
                end if;
                
            when STOP => 
                if back_sensor = '1' then
                    next_state <= WAIT_PASSWORD;
                else
                    next_state <= STOP;
                end if;
                
        end case; 
    end process;

    -- Counter Process for WAIT_PASSWORD
    process(clk, reset_n)
    begin
        if reset_n = '0' then
            counter_wait <= (others => '0');
        elsif rising_edge(clk) then
            if current_state = WAIT_PASSWORD then
                if counter_wait < 9 then
                    counter_wait <= counter_wait + 1;
                end if;
            else
                counter_wait <= (others => '0');
            end if;
        end if;
    end process;

    -- Counter Process for WRONG_PASS
    process(clk, reset_n)
    begin
        if reset_n = '0' then
            counter_wrong <= (others => '0');
        elsif rising_edge(clk) then
            if current_state = WRONG_PASS then
                if counter_wrong < 3 then
                    counter_wrong <= counter_wrong + 1;
                else
                    counter_wrong <= (others => '0');
                end if;
            else
                counter_wrong <= (others => '0');
            end if;
        end if;
    end process;

    -- Blink counter
    process(clk, reset_n)
    begin
        if reset_n = '0' then
            blink_counter <= (others => '0');
        elsif rising_edge(clk) then
            blink_counter <= blink_counter + 1;
        end if;
    end process;

    -- Output process
    process(clk)
        variable blink_fast : std_logic;
    begin
        blink_fast := blink_counter(0);
        
        if rising_edge(clk) then
            case current_state is
                when IDLE => 
                    green_tmp <= '0';
                    red_tmp   <= '0';
                    HEX_1     <= "1111111";
                    HEX_2     <= "1111111";
                    
                when WAIT_PASSWORD =>
                    green_tmp <= '0';
                    red_tmp   <= '1';
                    HEX_1     <= "0000110";
                    HEX_2     <= "0101011";
                    
                when WRONG_PASS =>
                    green_tmp <= '0';
                    red_tmp   <= blink_fast;
                    HEX_1     <= "0000110";
                    HEX_2     <= "0000110";
                    
                when RIGHT_PASS =>
                    green_tmp <= blink_fast;
                    red_tmp   <= '0';
                    HEX_1     <= "0000010";
                    HEX_2     <= "1000000";
                    
                when STOP => 
                    green_tmp <= '0';
                    red_tmp   <= blink_fast;
                    HEX_1     <= "0100100";
                    HEX_2     <= "0001100";
            end case;
        end if;
    end process;
    
    GREEN_LED <= green_tmp;
    RED_LED   <= red_tmp;

end architecture;

test.vhd
library ieee;
use ieee.std_logic_1164.all;
use ieee.numeric_std.all;

entity test is
end test;

architecture testbench of test is
    component Car_Parking_System_VHDL is
    port (
        clk, reset_n: in std_logic;
        front_sensor, back_sensor: in std_logic;
        password_1, password_2: in std_logic_vector(1 downto 0);
        GREEN_LED, RED_LED: out std_logic;
        HEX_1, HEX_2: out std_logic_vector(6 downto 0)
    );
    end component;

    signal clk_tb           : std_logic := '0';
    signal reset_n_tb       : std_logic := '0';
    signal front_sensor_tb  : std_logic := '0';
    signal back_sensor_tb   : std_logic := '0';
    signal password_1_tb    : std_logic_vector(1 downto 0) := "00";
    signal password_2_tb    : std_logic_vector(1 downto 0) := "00";
    signal GREEN_LED_tb     : std_logic;
    signal RED_LED_tb       : std_logic;
    signal HEX_1_tb         : std_logic_vector(6 downto 0);
    signal HEX_2_tb         : std_logic_vector(6 downto 0);

    constant clk_period : time := 200 ms;

begin
    clk_process : process
    begin
        while true loop
            clk_tb <= '0';
            wait for clk_period/2;
            clk_tb <= '1';
            wait for clk_period/2;
        end loop;
    end process;

    DUT: Car_Parking_System_VHDL
    port map (
        clk => clk_tb,
        reset_n => reset_n_tb,
        front_sensor => front_sensor_tb,
        back_sensor => back_sensor_tb,
        password_1 => password_1_tb,
        password_2 => password_2_tb,
        GREEN_LED => GREEN_LED_tb,
        RED_LED => RED_LED_tb,
        HEX_1 => HEX_1_tb,
        HEX_2 => HEX_2_tb
    );

    stimulus: process
    begin
        -- Initial Reset
        reset_n_tb <= '0';
        wait for clk_period * 2;
        reset_n_tb <= '1';
        
        -- No cars for 2 seconds
        wait for 2000 ms;
        
        -- ========== 1stCar 1 ==========
        -- Car 1 Approeaches
        front_sensor_tb <= '1';
        
        -- The system wait for 10 clock cycles (2 seconds) for checking the pw
        -- Meanwhile En and Stable-Red-Led by def of state machine
        wait for 2000 ms;
        
        -- 1st (wrong) attempt!
        password_1_tb <= "11";
        password_2_tb <= "11";
        -- system goes in WRONGPASS and waits
        wait for 1000 ms;
        
        -- After WRONG_PASS, go back in WAIT_PASSWORD and shows "En"
        -- Waits again 10 cycles to check the pw
        wait for 2000 ms;
        
        -- 2nd (correct) attempt! --> Good To Go!
        password_1_tb <= "01";
        password_2_tb <= "10";
        -- System oges in PASS and "Go" displayed
        
        -- Car 1 starts to enter (slowly total time= 3 seconds)
        front_sensor_tb <='0';
        -- After 2 sec, Car #2 approaches
        wait for 2000 ms;
        front_sensor_tb <= '1'; -- Car 2 Approched
        
        -- System in STOP as show "SP" 
        -- Waits for car1 to enter
        wait for 2000 ms;
        back_sensor_tb <= '1'; -- Car 1 entered
        wait for clk_period;
        back_sensor_tb <= '0';
        
        -- ========== Car 2 ==========
        -- After Car1 in inside, system in WAIT_PASSWORD and shows "En" + Reset Password in the machine
        password_1_tb <= "00";
        password_2_tb <= "00";
        
        -- Car 2 waits a little
        wait for 1500 ms;
        
        --  Car 2 enters the pw in 0.5 secondi
        -- btw the system waits 10 clks (2 seconds)  to check the pw
        -- So we wait still 0.5 secondi (totale 2 secondi dall'ingresso in WAIT_PASSWORD)
        wait for 500 ms;
        
        -- Car 2 puts correct pw
        password_1_tb <= "01";
        password_2_tb <= "10";
        
        -- System goes in RIGHT_PASS and shows "GO" 
        -- Car 2 takes 5 seconds to enter
        wait for 1000 ms;
        back_sensor_tb <= '1'; -- Car 2 starts to go through
        front_sensor_tb <= '0'; -- No Car Waiting
        wait for clk_period;
        back_sensor_tb <= '0'; -- Car 2 completely in
        front_sensor_tb <= '0';
        
        -- Fine simulazione
        wait for clk_period * 5;
        
        assert false report "Simulazione completata con successo!" severity note;
        wait;
    end process;

end architecture testbench;

sim.vcd
$date
  Sat Nov 15 12:33:56 2025
$end
$version
  GHDL v0
$end
$timescale
  1 fs
$end
$scope module standard $end
$upscope $end
$scope module std_logic_1164 $end
$upscope $end
$scope module numeric_std $end
$upscope $end
$scope module test $end
$var reg 1 ! clk_tb $end
$var reg 1 " reset_n_tb $end
$var reg 1 # front_sensor_tb $end
$var reg 1 $ back_sensor_tb $end
$var reg 2 % password_1_tb[1:0] $end
$var reg 2 & password_2_tb[1:0] $end
$var reg 1 ' green_led_tb $end
$var reg 1 ( red_led_tb $end
$var reg 7 ) hex_1_tb[6:0] $end
$var reg 7 * hex_2_tb[6:0] $end
$scope module dut $end
$var reg 1 + clk $end
$var reg 1 , reset_n $end
$var reg 1 - front_sensor $end
$var reg 1 . back_sensor $end
$var reg 2 / password_1[1:0] $end
$var reg 2 0 password_2[1:0] $end
$var reg 1 1 green_led $end
$var reg 1 2 red_led $end
$var reg 7 3 hex_1[6:0] $end
$var reg 7 4 hex_2[6:0] $end
$comment current_state is not handled $end
$comment next_state is not handled $end
$var reg 4 5 counter_wait[3:0] $end
$var reg 2 6 counter_wrong[1:0] $end
$var reg 1 7 red_tmp $end
$var reg 1 8 green_tmp $end
$var reg 2 9 blink_counter[1:0] $end
$var reg 1 : password_accepted $end
$var reg 1 ; password_checked $end
$upscope $end
$upscope $end
$enddefinitions $end
#0
0!
0"
0#
0$
b00 %
b00 &
U'
U(
bUUUUUUU )
bUUUUUUU *
0+
0,
0-
0.
b00 /
b00 0
U1
U2
bUUUUUUU 3
bUUUUUUU 4
b0000 5
b00 6
U7
U8
b00 9
0:
0;
#100000000000000
1!
0'
0(
b1111111 )
b1111111 *
1+
01
02
b1111111 3
b1111111 4
07
08
#200000000000000
0!
0+
#300000000000000
1!
1+
#400000000000000
0!
1"
0+
1,
#500000000000000
1!
1+
b01 9
#600000000000000
0!
0+
#700000000000000
1!
1+
b10 9
#800000000000000
0!
0+
#900000000000000
1!
1+
b11 9
#1000000000000000
0!
0+
#1100000000000000
1!
1+
b00 9
#1200000000000000
0!
0+
#1300000000000000
1!
1+
b01 9
#1400000000000000
0!
0+
#1500000000000000
1!
1+
b10 9
#1600000000000000
0!
0+
#1700000000000000
1!
1+
b11 9
#1800000000000000
0!
0+
#1900000000000000
1!
1+
b00 9
#2000000000000000
0!
0+
#2100000000000000
1!
1+
b01 9
#2200000000000000
0!
0+
#2300000000000000
1!
1+
b10 9
#2400000000000000
0!
1#
0+
1-
#2500000000000000
1!
1+
b11 9
#2600000000000000
0!
0+
#2700000000000000
1!
1(
b0000110 )
b0101011 *
1+
12
b0000110 3
b0101011 4
b0001 5
17
b00 9
#2800000000000000
0!
0+
#2900000000000000
1!
1+
b0010 5
b01 9
#3000000000000000
0!
0+
#3100000000000000
1!
1+
b0011 5
b10 9
#3200000000000000
0!
0+
#3300000000000000
1!
1+
b0100 5
b11 9
#3400000000000000
0!
0+
#3500000000000000
1!
1+
b0101 5
b00 9
#3600000000000000
0!
0+
#3700000000000000
1!
1+
b0110 5
b01 9
#3800000000000000
0!
0+
#3900000000000000
1!
1+
b0111 5
b10 9
#4000000000000000
0!
0+
#4100000000000000
1!
1+
b1000 5
b11 9
#4200000000000000
0!
0+
#4300000000000000
1!
1+
b1001 5
b00 9
X;
#4400000000000000
0!
b11 %
b11 &
0+
b11 /
b11 0
#4500000000000000
1!
1+
b01 9
#4600000000000000
0!
0+
#4700000000000000
1!
b0000110 *
1+
b0000110 4
b0000 5
b01 6
b10 9
#4800000000000000
0!
0+
#4900000000000000
1!
0(
1+
02
b10 6
07
b11 9
#5000000000000000
0!
0+
#5100000000000000
1!
1(
1+
12
b11 6
17
b00 9
#5200000000000000
0!
0+
#5300000000000000
1!
b0101011 *
1+
b0101011 4
b0001 5
b00 6
b01 9
#5400000000000000
0!
0+
#5500000000000000
1!
1+
b0010 5
b10 9
#5600000000000000
0!
0+
#5700000000000000
1!
1+
b0011 5
b11 9
#5800000000000000
0!
0+
#5900000000000000
1!
1+
b0100 5
b00 9
#6000000000000000
0!
0+
#6100000000000000
1!
1+
b0101 5
b01 9
#6200000000000000
0!
0+
#6300000000000000
1!
1+
b0110 5
b10 9
#6400000000000000
0!
0+
#6500000000000000
1!
1+
b0111 5
b11 9
#6600000000000000
0!
0+
#6700000000000000
1!
1+
b1000 5
b00 9
#6800000000000000
0!
0+
#6900000000000000
1!
1+
b1001 5
b01 9
#7000000000000000
0!
0+
#7100000000000000
1!
1+
b10 9
#7200000000000000
0!
0+
#7300000000000000
1!
0(
b0000110 *
1+
02
b0000110 4
b0000 5
b01 6
07
b11 9
#7400000000000000
0!
0#
b01 %
b10 &
0+
0-
b01 /
b10 0
#7500000000000000
1!
1(
1+
12
b10 6
17
b00 9
#7600000000000000
0!
0+
#7700000000000000
1!
0(
1+
02
b11 6
07
b01 9
#7800000000000000
0!
0+
#7900000000000000
1!
1(
b0101011 *
1+
12
b0101011 4
b0001 5
b00 6
17
b10 9
#8000000000000000
0!
0+
#8100000000000000
1!
1+
b0010 5
b11 9
#8200000000000000
0!
0+
#8300000000000000
1!
1+
b0011 5
b00 9
#8400000000000000
0!
0+
#8500000000000000
1!
1+
b0100 5
b01 9
#8600000000000000
0!
0+
#8700000000000000
1!
1+
b0101 5
b10 9
#8800000000000000
0!
0+
#8900000000000000
1!
1+
b0110 5
b11 9
#9000000000000000
0!
0+
#9100000000000000
1!
1+
b0111 5
b00 9
#9200000000000000
0!
0+
#9300000000000000
1!
1+
b1000 5
b01 9
#9400000000000000
0!
1#
0+
1-
#9500000000000000
1!
1+
b1001 5
b10 9
X:
#9600000000000000
0!
0+
#9700000000000000
1!
1+
b11 9
#9800000000000000
0!
0+
#9900000000000000
1!
1'
0(
b0000010 )
b1000000 *
1+
11
02
b0000010 3
b1000000 4
b0000 5
07
18
b00 9
#10000000000000000
0!
0+
#10100000000000000
1!
0'
1+
01
08
b01 9
#10200000000000000
0!
0+
#10300000000000000
1!
1'
1+
11
18
b10 9
#10400000000000000
0!
0+
#10500000000000000
1!
0'
1+
01
08
b11 9
#10600000000000000
0!
0+
#10700000000000000
1!
1'
1+
11
18
b00 9
#10800000000000000
0!
0+
#10900000000000000
1!
0'
1+
01
08
b01 9
#11000000000000000
0!
0+
#11100000000000000
1!
1'
1+
11
18
b10 9
#11200000000000000
0!
0+
#11300000000000000
1!
0'
1+
01
08
b11 9
#11400000000000000
0!
1$
0+
1.
#11500000000000000
1!
1'
1+
11
18
b00 9
#11600000000000000
0!
0$
b00 %
b00 &
0+
0.
b00 /
b00 0
#11700000000000000
1!
0'
b1111111 )
b1111111 *
1+
01
b1111111 3
b1111111 4
08
b01 9
#11800000000000000
0!
0+
#11900000000000000
1!
1(
b0000110 )
b0101011 *
1+
12
b0000110 3
b0101011 4
b0001 5
17
b10 9
#12000000000000000
0!
0+
#12100000000000000
1!
1+
b0010 5
b11 9
#12200000000000000
0!
0+
#12300000000000000
1!
1+
b0011 5
b00 9
#12400000000000000
0!
0+
#12500000000000000
1!
1+
b0100 5
b01 9
#12600000000000000
0!
0+
#12700000000000000
1!
1+
b0101 5
b10 9
#12800000000000000
0!
0+
#12900000000000000
1!
1+
b0110 5
b11 9
#13000000000000000
0!
0+
#13100000000000000
1!
1+
b0111 5
b00 9
#13200000000000000
0!
0+
#13300000000000000
1!
1+
b1000 5
b01 9
#13400000000000000
0!
0+
#13500000000000000
1!
1+
b1001 5
b10 9
#13600000000000000
0!
b01 %
b10 &
0+
b01 /
b10 0
#13700000000000000
1!
1+
b11 9
#13800000000000000
0!
0+
#13900000000000000
1!
1'
0(
b0000010 )
b1000000 *
1+
11
02
b0000010 3
b1000000 4
b0000 5
07
18
b00 9
#14000000000000000
0!
0+
#14100000000000000
1!
0'
1+
01
08
b01 9
#14200000000000000
0!
0+
#14300000000000000
1!
1'
1+
11
18
b10 9
#14400000000000000
0!
0+
#14500000000000000
1!
0'
1+
01
08
b11 9
#14600000000000000
0!
0#
1$
0+
0-
1.
#14700000000000000
1!
1'
1+
11
18
b00 9
#14800000000000000
0!
0$
0+
0.
#14900000000000000
1!
0'
b1111111 )
b1111111 *
1+
01
b1111111 3
b1111111 4
08
b01 9
#15000000000000000
0!
0+
#15100000000000000
1!
1+
b10 9
#15200000000000000
0!
0+
#15300000000000000
1!
1+
b11 9
#15400000000000000
0!
0+
#15500000000000000
1!
1+
b00 9
#15600000000000000
0!
0+
#15700000000000000
1!
1+
b01 9
#15800000000000000
0!
0+
#15900000000000000
1!
1+
b10 9
#16000000000000000
0!
0+
#16100000000000000
1!
1+
b11 9
#16200000000000000
0!
0+
#16300000000000000
1!
1+
b00 9
#16400000000000000
0!
0+
#16500000000000000
1!
1+
b01 9
#16600000000000000
0!
0+
#16700000000000000
1!
1+
b10 9
#16800000000000000
0!
0+
#16900000000000000
1!
1+
b11 9
#17000000000000000
0!
0+
#17100000000000000
1!
1+
b00 9
#17200000000000000
0!
0+
#17300000000000000
1!
1+
b01 9
#17400000000000000
0!
0+
#17500000000000000
1!
1+
b10 9
#17600000000000000
0!
0+
#17700000000000000
1!
1+
b11 9
#17800000000000000
0!
0+
#17900000000000000
1!
1+
b00 9
#18000000000000000
0!
0+
#18100000000000000
1!
1+
b01 9
#18200000000000000
0!
0+
#18300000000000000
1!
1+
b10 9
#18400000000000000
0!
0+
#18500000000000000
1!
1+
b11 9
#18600000000000000
0!
0+
#18700000000000000
1!
1+
b00 9
#18800000000000000
0!
0+
#18900000000000000
1!
1+
b01 9
#19000000000000000
0!
0+
#19100000000000000
1!
1+
b10 9
#19200000000000000
0!
0+
#19300000000000000
1!
1+
b11 9
#19400000000000000
0!
0+
#19500000000000000
1!
1+
b00 9
#19600000000000000
0!
0+
#19700000000000000
1!
1+
b01 9
#19800000000000000
0!
0+
#19900000000000000
1!
1+
b10 9
#20000000000000000
0!
0+
#20100000000000000
1!
1+
b11 9
#20200000000000000
0!
0+
#20300000000000000
1!
1+
b00 9
#20400000000000000
0!
0+
#20500000000000000
1!
1+
b01 9
#20600000000000000
0!
0+
#20700000000000000
1!
1+
b10 9
#20800000000000000
0!
0+
#20900000000000000
1!
1+
b11 9
#21000000000000000
0!
0+
#21100000000000000
1!
1+
b00 9
#21200000000000000
0!
0+
#21300000000000000
1!
1+
b01 9
#21400000000000000
0!
0+
#21500000000000000
1!
1+
b10 9
#21600000000000000
0!
0+
#21700000000000000
1!
1+
b11 9
#21800000000000000
0!
0+
#21900000000000000
1!
1+
b00 9
#22000000000000000
0!
0+
#22100000000000000
1!
1+
b01 9
#22200000000000000
0!
0+
#22300000000000000
1!
1+
b10 9
#22400000000000000
0!
0+
#22500000000000000
1!
1+
b11 9
#22600000000000000
0!
0+
#22700000000000000
1!
1+
b00 9
#22800000000000000
0!
0+
#22900000000000000
1!
1+
b01 9
#23000000000000000
0!
0+
#23100000000000000
1!
1+
b10 9
#23200000000000000
0!
0+
#23300000000000000
1!
1+
b11 9
#23400000000000000
0!
0+
#23500000000000000
1!
1+
b00 9
#23600000000000000
0!
0+
#23700000000000000
1!
1+
b01 9
#23800000000000000
0!
0+
#23900000000000000
1!
1+
b10 9
#24000000000000000
0!
0+
#24100000000000000
1!
1+
b11 9
#24200000000000000
0!
0+
#24300000000000000
1!
1+
b00 9
#24400000000000000
0!
0+
#24500000000000000
1!
1+
b01 9
#24600000000000000
0!
0+
#24700000000000000
1!
1+
b10 9
#24800000000000000
0!
0+
#24900000000000000
1!
1+
b11 9
#25000000000000000
0!
0+
#25100000000000000
1!
1+
b00 9
#25200000000000000
0!
0+
#25300000000000000
1!
1+
b01 9
#25400000000000000
0!
0+
#25500000000000000
1!
1+
b10 9
#25600000000000000
0!
0+
#25700000000000000
1!
1+
b11 9
#25800000000000000
0!
0+
#25900000000000000
1!
1+
b00 9
#26000000000000000
0!
0+
#26100000000000000
1!
1+
b01 9
#26200000000000000
0!
0+
#26300000000000000
1!
1+
b10 9
#26400000000000000
0!
0+
#26500000000000000
1!
1+
b11 9
#26600000000000000
0!
0+
#26700000000000000
1!
1+
b00 9
#26800000000000000
0!
0+
#26900000000000000
1!
1+
b01 9
#27000000000000000
0!
0+
#27100000000000000
1!
1+
b10 9
#27200000000000000
0!
0+
#27300000000000000
1!
1+
b11 9
#27400000000000000
0!
0+
#27500000000000000
1!
1+
b00 9
#27600000000000000
0!
0+
#27700000000000000
1!
1+
b01 9
#27800000000000000
0!
0+
#27900000000000000
1!
1+
b10 9
#28000000000000000
0!
0+
#28100000000000000
1!
1+
b11 9
#28200000000000000
0!
0+
#28300000000000000
1!
1+
b00 9
#28400000000000000
0!
0+
#28500000000000000
1!
1+
b01 9
#28600000000000000
0!
0+
#28700000000000000
1!
1+
b10 9
#28800000000000000
0!
0+
#28900000000000000
1!
1+
b11 9
#29000000000000000
0!
0+
#29100000000000000
1!
1+
b00 9
#29200000000000000
0!
0+
#29300000000000000
1!
1+
b01 9
#29400000000000000
0!
0+
#29500000000000000
1!
1+
b10 9
#29600000000000000
0!
0+
#29700000000000000
1!
1+
b11 9
#29800000000000000
0!
0+
#29900000000000000
1!
1+
b00 9
